LICENSE.txt
README.md
setup.cfg
setup.py
bin/Genesis2.pl
genesis2/__init__.py
genesis2.egg-info/PKG-INFO
genesis2.egg-info/SOURCES.txt
genesis2.egg-info/dependency_links.txt
genesis2.egg-info/top_level.txt